techspec/__init__.py
techspec/__main__.py
techspec/py.typed
techspec/schema.json
techspec/cli/__init__.py
techspec/cli/app.py
techspec/cli/container.py
techspec/cli/main.py
techspec/cli/actions/__init__.py
techspec/cli/actions/code.py
techspec/cli/actions/schema.py
techspec/cli/groups/__init__.py
techspec/cli/groups/code.py
techspec/cli/groups/schema.py
techspec/generator/__init__.py
techspec/generator/dtos.py
techspec/generator/exceptions.py
techspec/generator/service.py
techspec/schema/__init__.py
techspec/schema/dtos.py
techspec/schema/exceptions.py
techspec/schema/json_schema.py
techspec/schema/service.py
techspec/schema/utils.py
tech_spec-1.0.46.dist-info/METADATA
tech_spec-1.0.46.dist-info/WHEEL
tech_spec-1.0.46.dist-info/entry_points.txt
tech_spec-1.0.46.dist-info/top_level.txt
tech_spec-1.0.46.dist-info/RECORD
