Metadata-Version: 2.1
Name: tech-spec
Version: 1.0.46
Summary: Tech spec for code generation
Author: Vladimir Vojtenko
Author-email: vladimirdev635@gmail.com
License: MIT
Requires-Dist: typer[all]
Requires-Dist: astor
Requires-Dist: pyyaml
Requires-Dist: jsonschema
Requires-Dist: dependency-injector
